setup.py
yafsm.py
yafsm.egg-info/PKG-INFO
yafsm.egg-info/SOURCES.txt
yafsm.egg-info/dependency_links.txt
yafsm.egg-info/top_level.txt