Metadata-Version: 1.0
Name: yafsm
Version: 0.1
Summary: Yeah! Another Finite State Machine
Home-page: https://github.com/jeffkit/yafsm/
Author: jeff kit
Author-email: jeff@toraysoft.com
License: UNKNOWN
Platform: UNKNOWN
